mpfutils/__init__.py
mpfutils/ai/__init__.py
mpfutils/ai/oai.py
mpfutils/azstorage/__init__.py
mpfutils/azstorage/azs_container.py
mpfutils/charts/__init__.py
mpfutils/charts/charts.py
mpfutils/cosmosdb/__init__.py
mpfutils/cosmosdb/cdb_client.py
mpfutils-0.4.6.dist-info/METADATA
mpfutils-0.4.6.dist-info/WHEEL
mpfutils-0.4.6.dist-info/licenses/LICENSE
mpfutils-0.4.6.dist-info/RECORD
